{
  "main": {
    "id": "05e3c730ee648a5f",
    "type": "split",
    "children": [
      {
        "id": "a5c9aecd6d1a4008",
        "type": "tabs",
        "children": [
          {
            "id": "37429ca2a7c1d461",
            "type": "leaf",
            "state": {
              "type": "markdown",
              "state": {
                "file": "数据的表示和运算.md",
                "mode": "source",
                "source": false
              },
              "icon": "lucide-file",
              "title": "数据的表示和运算"
            }
          }
        ]
      }
    ],
    "direction": "vertical"
  },
  "left": {
    "id": "2154bd6f1176c81b",
    "type": "split",
    "children": [
      {
        "id": "334e623daa0ad5e2",
        "type": "tabs",
        "children": [
          {
            "id": "7c3e9c69aca45163",
            "type": "leaf",
            "state": {
              "type": "file-explorer",
              "state": {
                "sortOrder": "byCreatedTimeReverse",
                "autoReveal": false
              },
              "icon": "lucide-folder-closed",
              "title": "文件列表"
            }
          },
          {
            "id": "8fe57d735774d914",
            "type": "leaf",
            "state": {
              "type": "search",
              "state": {
                "query": "",
                "matchingCase": false,
                "explainSearch": false,
                "collapseAll": false,
                "extraContext": false,
                "sortOrder": "alphabetical"
              },
              "icon": "lucide-search",
              "title": "搜索"
            }
          },
          {
            "id": "d1414f6e27143cd7",
            "type": "leaf",
            "state": {
              "type": "bookmarks",
              "state": {},
              "icon": "lucide-bookmark",
              "title": "书签"
            }
          }
        ]
      }
    ],
    "direction": "horizontal",
    "width": 292.5
  },
  "right": {
    "id": "b8f786d009ce6b5e",
    "type": "split",
    "children": [
      {
        "id": "d6a9d8ad3bc72f4b",
        "type": "tabs",
        "children": [
          {
            "id": "701ca53cb0809cdb",
            "type": "leaf",
            "state": {
              "type": "backlink",
              "state": {
                "file": "数据结构与算法.md",
                "collapseAll": false,
                "extraContext": false,
                "sortOrder": "alphabetical",
                "showSearch": false,
                "searchQuery": "",
                "backlinkCollapsed": false,
                "unlinkedCollapsed": true
              },
              "icon": "links-coming-in",
              "title": "数据结构与算法 的反向链接列表"
            }
          },
          {
            "id": "fb575ee2e94a4475",
            "type": "leaf",
            "state": {
              "type": "outgoing-link",
              "state": {
                "file": "计算机科学与技术/图.md",
                "linksCollapsed": true,
                "unlinkedCollapsed": false
              },
              "icon": "links-going-out",
              "title": "图 的出链列表"
            }
          },
          {
            "id": "7ee69143e5ee3509",
            "type": "leaf",
            "state": {
              "type": "tag",
              "state": {
                "sortOrder": "frequency",
                "useHierarchy": true,
                "showSearch": false,
                "searchQuery": ""
              },
              "icon": "lucide-tags",
              "title": "标签"
            }
          },
          {
            "id": "568d8adda81d6ad0",
            "type": "leaf",
            "state": {
              "type": "all-properties",
              "state": {
                "sortOrder": "frequency",
                "showSearch": false,
                "searchQuery": ""
              },
              "icon": "lucide-archive",
              "title": "添加笔记属性"
            }
          },
          {
            "id": "91219ae3b29bcbf7",
            "type": "leaf",
            "state": {
              "type": "outline",
              "state": {
                "file": "计算机科学与技术/图.md",
                "followCursor": false,
                "showSearch": false,
                "searchQuery": ""
              },
              "icon": "lucide-list",
              "title": "图 的大纲"
            }
          },
          {
            "id": "44b3ad8b91353c65",
            "type": "leaf",
            "state": {
              "type": "git-view",
              "state": {},
              "icon": "git-pull-request",
              "title": "Source Control"
            }
          }
        ],
        "currentTab": 5
      }
    ],
    "direction": "horizontal",
    "width": 300,
    "collapsed": true
  },
  "left-ribbon": {
    "hiddenItems": {
      "switcher:打开快速切换": false,
      "graph:查看关系图谱": false,
      "canvas:新建白板": false,
      "daily-notes:打开/创建今天的日记": false,
      "templates:插入模板": false,
      "command-palette:打开命令面板": false,
      "bases:新建数据库": false,
      "obsidian-git:Open Git source control": false
    }
  },
  "active": "37429ca2a7c1d461",
  "lastOpenFiles": [
    "bookmanager/b636fa04af0431966f83d34cd58c64d4.jpg",
    "数据的表示和运算.md",
    "MIPS指令系统.md",
    "bookmanager/表格_20260320.csv",
    "未命名.md",
    "未命名.base",
    "bookmanager/f2ef4abb2adcbe225888d1fa96245f85.jpg",
    "bookmanager/4cf5d3a6c05f4bcd09c36962e2e68b95.jpg",
    "bookmanager/d3c5300149c84d3f4e2e7892c53a1f4b.jpg",
    "bookmanager/第三章系统总线.pdf",
    "bookmanager/b2360053df7ff600f62615857f5b4107.jpg",
    "计算机科学与技术/计算机组成原理.md",
    "计算机科学与技术/~$第三章系统总线.pptx",
    "bookmanager/5c56cb09d0178a65e98a263fc2868c41 1.jpg",
    "bookmanager/3f3e5087573127d70d149be3056a94ad.jpg",
    "bookmanager/5c56cb09d0178a65e98a263fc2868c41.jpg",
    "bookmanager/7dbfd1309402a1cfa2e355afdef7fb64.jpg",
    "bookmanager/39f794a5df06fdd1ca2cef79f731c5c1.jpg",
    "计算机科学与技术/人工智能.md",
    "未命名",
    "微积分/欧拉麦克劳林公式.md",
    "微积分",
    "计算机科学与技术/编译原理.md",
    "计算机科学与技术/计算机网络.md",
    "bookmanager/~$第三章系统总线.pptx",
    "计算机科学与技术/第三章系统总线.pptx",
    "bookmanager",
    "新建文件夹",
    "计算机科学与技术/图.md",
    "2026-03-12.md",
    "计算机科学与技术/计算机科学与技术.md",
    "计算机科学与技术/C++ 程序设计.md",
    "计算机科学与技术/数据结构与算法.md",
    "计算机科学与技术/树.md",
    "计算机科学与技术/队列.md",
    "计算机科学与技术/栈.md",
    "计算机科学与技术/查找算法.md",
    "计算机科学与技术/排序算法.md",
    "计算机科学与技术/线性表.md",
    "计算机科学与技术/操作系统.md",
    "计算机科学与技术/高等数学.md",
    "计算机科学与技术/离散数学.md",
    "创建链接.md",
    "欢迎.md",
    "# 计算机科学与技术（MOC） ## 核心课程 - [[数据结构]] - [[编译原理]] - [[操作系统]] - [[计算机网络]] - [[数据库系统]] - [[算法设计与分析]]  ## 基础课程 - [[高等数学]] - [[离散数学]] - [[C++ 程序设计]]  ## 方向分支 - [[人工智能]] - [[软件工程]] - [[计算机体系结构]].md"
  ]
}